AUTHORS.rst
CONTRIBUTING.rst
HISTORY.rst
LICENSE
MANIFEST.in
README.rst
setup.cfg
setup.py
docs/Makefile
docs/authors.rst
docs/conf.py
docs/contributing.rst
docs/history.rst
docs/index.rst
docs/installation.rst
docs/make.bat
docs/readme.rst
docs/usage.rst
include/ngl_cuda.cuh
include/ngl_cuda.h
nglpy_cuda/FAISSSearchIndex.py
nglpy_cuda/Graph.py
nglpy_cuda/ProbabilisticGraph.py
nglpy_cuda/SKLSearchIndex.py
nglpy_cuda/SearchIndex.py
nglpy_cuda/__init__.py
nglpy_cuda/core.cpp
nglpy_cuda/utils.py
nglpy_cuda.egg-info/PKG-INFO
nglpy_cuda.egg-info/SOURCES.txt
nglpy_cuda.egg-info/dependency_links.txt
nglpy_cuda.egg-info/not-zip-safe
nglpy_cuda.egg-info/requires.txt
nglpy_cuda.egg-info/top_level.txt
src/ngl_cuda.cu
src/test.cpp