Metadata-Version: 1.1
Name: nglpy-cuda
Version: 0.2.0
Summary: TODO
Home-page: https://github.com/maljovec/nglpy_cuda
Author: Daniel Patrick Maljovec
Author-email: maljovec002@gmail.com
License: BSD license
Keywords: nglpy_cuda
Platform: UNKNOWN
Classifier: Development Status :: 2 - Pre-Alpha
Classifier: Intended Audience :: Developers
Classifier: License :: OSI Approved :: BSD License
Classifier: Natural Language :: English
Classifier: Programming Language :: Python :: 2
Classifier: Programming Language :: Python :: 2.7
Classifier: Programming Language :: Python :: 3
Classifier: Programming Language :: Python :: 3.4
Classifier: Programming Language :: Python :: 3.5
Classifier: Programming Language :: Python :: 3.6
